nchess/__init__.py
nchess/const/__init__.py
nchess/core/__init__.py
nchess/core/__init__.pyi
nchess/core/nchess_core.cp312-win_amd64.pyd
nchess/core/src/PyBB.c
nchess/core/src/PyBB.h
nchess/core/src/array_conversion.c
nchess/core/src/array_conversion.h
nchess/core/src/bb_functions.c
nchess/core/src/bb_functions.h
nchess/core/src/common.c
nchess/core/src/common.h
nchess/core/src/module.c
nchess/core/src/pybb_methods.c
nchess/core/src/pybb_methods.h
nchess/core/src/pyboard.c
nchess/core/src/pyboard.h
nchess/core/src/pyboard_getset.c
nchess/core/src/pyboard_getset.h
nchess/core/src/pyboard_methods.c
nchess/core/src/pyboard_methods.h
nchess/core/src/pymove.c
nchess/core/src/pymove.h
nchess/core/src/pymove_getset.c
nchess/core/src/pymove_getset.h
nchess/core/src/square_functions.c
nchess/core/src/square_functions.h
nchess-1.3.1.dist-info/licenses/LICENSE
nchess-1.3.1.dist-info/METADATA
nchess-1.3.1.dist-info/WHEEL
nchess-1.3.1.dist-info/top_level.txt
nchess-1.3.1.dist-info/RECORD
