Metadata-Version: 2.4
Name: nchess
Version: 1.3.1
Summary: High-performance chess library written in C
Home-page: https://github.com/MNourMoslem/NChess
Author: MNMoslem
Author-email: MNMoslem <normoslem256@gmail.com>
License: MIT
Project-URL: Homepage, https://github.com/MNourMoslem/NChess
Classifier: Programming Language :: Python :: 3
Classifier: Programming Language :: C
Classifier: License :: OSI Approved :: MIT License
Classifier: Operating System :: OS Independent
Classifier: Topic :: Games/Entertainment :: Board Games
Requires-Python: >=3.7
License-File: LICENSE
Requires-Dist: numpy>=1.18.0
Dynamic: author
Dynamic: home-page
Dynamic: license-file
Dynamic: requires-python
